{
  "UI": {
    "FILE": "File",
    "OPEN": "Open",
    "FOLLOW": "Follow",
    "OPEN_FILES": "Open Files",
    "APPEND_FILES": "Append Files",
    "OPEN_RECENTS": "Open Recents",
    "CLOSE": "Close",
    "EXIT": "Exit",
    "SETTING": "Settings",
    "ADB": "ADB",
    "FONT": "Font",
    "LOG": "Log",
    "START": "Start",
    "STOP": "Stop",
    "PAUSE": "Pause",
    "CLEAR_VIEWS": "Clear Views",
    "ROTATION": "Rotation",
    "FIRST": "First",
    "LAST": "Last",
    "BOLD": "Bold",
    "HIDE": "Hide",
    "TAG": "Tag",
    "PID": "PID",
    "TID": "TID",
    "FILTER": "Filter",
    "WINDOWED_MODE": "Windowed Mode",
    "VIEW": "View",
    "VIEW_FULL": "View Fullscreen",
    "HELP": "Help",
    "ABOUT": "About",
    "BOOKMARKS": "Bookmarks",
    "FULL": "Full",
    "INCREMENTAL": "Incremental",
    "HIGHLIGHT": "Highlight",
    "LOGLEVEL": "Log Level",
    "SCROLL_BACK": "Scroll Back",
    "CLEAR_SAVE": "Clear/Save",
    "LOGFILE": "Log File",
    "CONNECT": "Connect",
    "REFRESH": "Refresh",
    "DISCONNECT": "Disconnect",
    "APPLY": "Apply",
    "SCROLL_BACK_LINES": "Scroll Back Lines",
    "SPLIT_FILE": "Split File",
    "COLOR": "Color",
    "FILTERS": "Filters",
    "KEEP": "Keep",
    "OK": "OK",
    "CANCEL": "Cancel",
    "NEW": "New",
    "COPY": "Copy",
    "EDIT": "Edit",
    "DELETE": "Delete",
    "SAVE": "Save",
    "SELECT": "Select",
    "ADB_PATH": "ADB Path",
    "LOG_PATH": "Log Path",
    "SIZE": "Size",
    "CONNECTED": "Connected",
    "NOT_CONNECTED": "Not Connected",
    "APPEND": "Append",
    "MSG_SELECT_OPEN_MODE": "Select Open Mode",
    "NONE": "None",
    "ADD_FILTER": "Add Filter",
    "ADD_CMD": "Add Command",
    "COMMANDS": "Commands",
    "RETRY_ADB": "Retry ADB",
    "FILTER_STYLE": "Filter Style",
    "LOOK_AND_FEEL": "Look and Feel",
    "FULL_LOG_TABLE": "Full Log Table",
    "FILTER_LOG_TABLE": "Filter Log Table",
    "BUILT_IN_SCHEMES": "Built-In Schemes",
    "LIGHT": "Light",
    "DARK": "Dark",
    "APPEARANCE": "Appearance",
    "OPTIONS": "Options",
    "LOG_CMD": "Log Command",
    "NOT_FOUND": "Not Found",
    "ADD_INCLUDE": "Add Include",
    "ADD_EXCLUDE": "Add Exclude",
    "ADD_SEARCH": "Add Search",
    "SET_SEARCH": "Set Search",
    "SEARCH": "Search",
    "CMD": "Command"
  },
  "TOOL_TIP": {
    "START_BTN": "Start adb logcat and receive logs",
    "PAUSE_BTN": "Pause adb logcat",
    "STOP_BTN": "Stop adb logcat",
    "CLEAR_BTN": "Clear log view",
    "SAVE_BTN": "Save new file",
    "DEVICES_COMBO": "List of connected devices or an address to connect to\n When the Enter key (or ctrl-r) is pressed, log reception starts after reconnection",
    "CONNECT_BTN": "adb connect [address]",
    "REFRESH_BTN": "Get list of connected devices",
    "DISCONNECT_BTN": "adb disconnect",
    "SCROLL_BACK_TF": "Number of log lines to keep in the log view (0: no limit)",
    "SCROLL_BACK_SPLIT_CHK": "Save file is changed every number of scroll lines",
    "SCROLL_BACK_APPLY_BTN": "Apply Line Count and File Split",
    "SCROLL_BACK_KEEP_TOGGLE": "Log is kept in the log view, used when the log is pushed up by the number of applied lines when reviewing the log",
    "ROTATION_BTN": "Change log views position up/down, left/right",
    "CASE_TOGGLE": "Log filter case-sensitive",
    "FILTER_LIST_BTN": "Manage frequently used filters",
    "LOG_TOGGLE": "Full log filter",
    "LOG_COMBO": "Regex support, filter: search, -filter: exclude search, ex filter1|filter2|-exclude1",
    "TAG_TOGGLE": "Tag filter",
    "TAG_COMBO": "Regex support, filter: search, -filter: exclude search, ex filter1|filter2|-exclude1",
    "PID_TOGGLE": "PID filter",
    "PID_COMBO": "Regex support, filter: search, -filter: exclude search, ex filter1|filter2|-exclude1",
    "TID_TOGGLE": "TID filter",
    "TID_COMBO": "Regex support, filter: search, -filter: exclude search, ex filter1|filter2|-exclude1",
    "BOLD_TOGGLE": "Change text to bold only",
    "BOLD_COMBO": "Regex support ex text1|text2",
    "VIEW_FIRST_BTN": "Go to first line",
    "VIEW_LAST_BTN": "Go to last line",
    "VIEW_PID_TOGGLE": "Highlight PID",
    "VIEW_TID_TOGGLE": "Highlight TID",
    "VIEW_TAG_TOGGLE": "Highlight tags",
    "VIEW_FULL_TOGGLE": "Show full log",
    "VIEW_BOOKMARKS_TOGGLE": "Show bookmarks only",
    "VIEW_WINDOWED_MODE_BTN": "Move the view to a new window",
    "SAVED_FILE_TF": "Saved file name",
    "ADD_FILTER_BTN": "Open filter list(add filter)",
    "ADD_CMD_BTN": "Open cmd list(add cmd)",
    "CMD_LIST_BTN": "Manage frequently used cmds",
    "RETRY_ADB_TOGGLE": "Auto retry when failed to receive log",
    "START_FOLLOW_BTN": "Append additional logs as the file grows",
    "STOP_FOLLOW_BTN": "Stop append logs",
    "LOG_CMD_COMBO": "Edit Log commands : Setting > adb",
    "SEARCH_COMBO": "Searching View : filtered log, full log",
    " SEARCH_CASE_TOGGLE": "Search case-sensitive",
    "SEARCH_PREV_BTN": "F3 : Move to Previous",
    "SEARCH_NEXT_BTN": "F4 : Move to Next",
    "SEARCH_TARGET_LABEL": "ESC : Close search bar"
  }
}